telegram_phone_number_checker/main.py
telegram_phone_number_checker-1.1.0.dist-info/LICENSE
telegram_phone_number_checker-1.1.0.dist-info/METADATA
telegram_phone_number_checker-1.1.0.dist-info/WHEEL
telegram_phone_number_checker-1.1.0.dist-info/entry_points.txt
telegram_phone_number_checker-1.1.0.dist-info/RECORD
