Metadata-Version: 2.1
Name: telegram-phone-number-checker
Version: 1.1.0
Summary: Check if phone numbers are connected to Telegram accounts.
Home-page: https://github.com/bellingcat/telegram-phone-number-checker
License: MIT
Author: Bellingcat
Requires-Python: >=3.9,<4.0
Classifier: License :: OSI Approved :: MIT License
Classifier: Programming Language :: Python :: 3
Classifier: Programming Language :: Python :: 3.9
Classifier: Programming Language :: Python :: 3.10
Classifier: Programming Language :: Python :: 3.11
Classifier: Programming Language :: Python :: 3.12
Requires-Dist: anyio (==4.2.0)
Requires-Dist: click (==8.1.7)
Requires-Dist: exceptiongroup (==1.2.0)
Requires-Dist: idna (==3.6)
Requires-Dist: pyaes (==1.6.1)
Requires-Dist: pyasn1 (==0.5.1)
Requires-Dist: python-dotenv (==1.0.1)
Requires-Dist: rsa (==4.9)
Requires-Dist: sniffio (==1.3.0)
Requires-Dist: telethon (==1.33.1)
Requires-Dist: typing-extensions (==4.9.0)
Project-URL: Bug Tracker, https://github.com/bellingcat/telegram-phone-number-checker/issues
Project-URL: Repository, https://github.com/bellingcat/telegram-phone-number-checker
